README.md
setup.cfg
setup.py
django_validator/__init__.py
django_validator/converters.py
django_validator/decorators.py
django_validator/exceptions.py
django_validator/status.py
django_validator/validators.py
django_validator.egg-info/PKG-INFO
django_validator.egg-info/SOURCES.txt
django_validator.egg-info/dependency_links.txt
django_validator.egg-info/requires.txt
django_validator.egg-info/top_level.txt