Metadata-Version: 1.0
Name: django-validator
Version: 0.3.0
Summary: Django validator with decorators.
Home-page: https://github.com/romain-li/django-validator
Author: romain_li
Author-email: romain_li@163.com
License: MIT
Keywords: validator
Platform: UNKNOWN
